[
    {
        "titre_affiche": "Death Note",
        "titre_recherche": "Death Note",
        "url_adkami": "https://www.adkami.com/anime/24",
        "source": "Enigme_et_Policier",
        "score_mal": 8.62,
        "popularite_members": 4279935,
        "image_url": "https://myanimelist.net/images/anime/1079/138100.jpg"
    },
    {
        "titre_affiche": "Death Note",
        "titre_recherche": "Death Note",
        "url_adkami": "https://www.adkami.com/anime/24",
        "source": "Enigme_et_Policier",
        "score_mal": 8.62,
        "popularite_members": 4279935,
        "image_url": "https://myanimelist.net/images/anime/1079/138100.jpg"
    },
    {
        "titre_affiche": "Psycho-Pass",
        "titre_recherche": "Psycho-Pass",
        "url_adkami": "https://www.adkami.com/anime/203",
        "source": "Enigme_et_Policier",
        "score_mal": 8.33,
        "popularite_members": 1744957,
        "image_url": "https://myanimelist.net/images/anime/1314/142015.jpg"
    },
    {
        "titre_affiche": "Psycho-Pass Extended Edition",
        "titre_recherche": "Psycho-Pass Extended Edition",
        "url_adkami": "https://www.adkami.com/anime/1706",
        "source": "Enigme_et_Policier",
        "score_mal": 8.33,
        "popularite_members": 1744957,
        "image_url": "https://myanimelist.net/images/anime/1314/142015.jpg"
    },
    {
        "titre_affiche": "Psycho-Pass",
        "titre_recherche": "Psycho-Pass",
        "url_adkami": "https://www.adkami.com/anime/203",
        "source": "Enigme_et_Policier",
        "score_mal": 8.33,
        "popularite_members": 1744957,
        "image_url": "https://myanimelist.net/images/anime/1314/142015.jpg"
    },
    {
        "titre_affiche": "Bungou Stray Dogs",
        "titre_recherche": "Bungou Stray Dogs",
        "url_adkami": "https://www.adkami.com/anime/1745",
        "source": "Enigme_et_Policier",
        "score_mal": 7.8,
        "popularite_members": 1547869,
        "image_url": "https://myanimelist.net/images/anime/3/79409.jpg"
    },
    {
        "titre_affiche": "Bungou Stray Dogs",
        "titre_recherche": "Bungou Stray Dogs",
        "url_adkami": "https://www.adkami.com/anime/1745",
        "source": "Enigme_et_Policier",
        "score_mal": 7.8,
        "popularite_members": 1547869,
        "image_url": "https://myanimelist.net/images/anime/3/79409.jpg"
    },
    {
        "titre_affiche": "Zankyou no Terror",
        "titre_recherche": "Zankyou no Terror",
        "url_adkami": "https://www.adkami.com/anime/1186",
        "source": "Enigme_et_Policier",
        "score_mal": 8.08,
        "popularite_members": 1276760,
        "image_url": "https://myanimelist.net/images/anime/1417/117422.jpg"
    },
    {
        "titre_affiche": "Zankyou no Terror",
        "titre_recherche": "Zankyou no Terror",
        "url_adkami": "https://www.adkami.com/anime/1186",
        "source": "Enigme_et_Policier",
        "score_mal": 8.08,
        "popularite_members": 1276760,
        "image_url": "https://myanimelist.net/images/anime/1417/117422.jpg"
    },
    {
        "titre_affiche": "Danganronpa: Kibou no Gakuen to Zetsubou no Koukousei The Animation",
        "titre_recherche": "Danganronpa: Kibou no Gakuen to Zetsubou no Koukousei The Animation",
        "url_adkami": "https://www.adkami.com/anime/758",
        "source": "Enigme_et_Policier",
        "score_mal": 7.19,
        "popularite_members": 1004878,
        "image_url": "https://myanimelist.net/images/anime/4/51463.jpg"
    },
    {
        "titre_affiche": "Danganronpa: Kibou no Gakuen to Zetsubou no Koukousei The Animation",
        "titre_recherche": "Danganronpa: Kibou no Gakuen to Zetsubou no Koukousei The Animation",
        "url_adkami": "https://www.adkami.com/anime/758",
        "source": "Enigme_et_Policier",
        "score_mal": 7.19,
        "popularite_members": 1004878,
        "image_url": "https://myanimelist.net/images/anime/4/51463.jpg"
    },
    {
        "titre_affiche": "Darker than Black: Kuro no Keiyakusha",
        "titre_recherche": "Darker than Black: Kuro no Keiyakusha",
        "url_adkami": "https://www.adkami.com/anime/266",
        "source": "Enigme_et_Policier",
        "score_mal": 8.04,
        "popularite_members": 1004725,
        "image_url": "https://myanimelist.net/images/anime/5/19570.jpg"
    },
    {
        "titre_affiche": "Darker than Black: Kuro no Keiyakusha",
        "titre_recherche": "Darker than Black: Kuro no Keiyakusha",
        "url_adkami": "https://www.adkami.com/anime/266",
        "source": "Enigme_et_Policier",
        "score_mal": 8.04,
        "popularite_members": 1004725,
        "image_url": "https://myanimelist.net/images/anime/5/19570.jpg"
    },
    {
        "titre_affiche": "Higurashi no Naku Koro ni [Saison 1]",
        "titre_recherche": "Higurashi no Naku Koro ni [Saison 1]",
        "url_adkami": "https://www.adkami.com/anime/325",
        "source": "Enigme_et_Policier",
        "score_mal": 7.87,
        "popularite_members": 856219,
        "image_url": "https://myanimelist.net/images/anime/12/19634.jpg"
    },
    {
        "titre_affiche": "Higurashi no Naku Koro ni [Saison 1]",
        "titre_recherche": "Higurashi no Naku Koro ni [Saison 1]",
        "url_adkami": "https://www.adkami.com/anime/325",
        "source": "Enigme_et_Policier",
        "score_mal": 7.87,
        "popularite_members": 856219,
        "image_url": "https://myanimelist.net/images/anime/12/19634.jpg"
    },
    {
        "titre_affiche": "Koukaku Kidoutai",
        "titre_recherche": "Koukaku Kidoutai",
        "url_adkami": "https://www.adkami.com/anime/4314",
        "source": "Enigme_et_Policier",
        "score_mal": 8.27,
        "popularite_members": 701685,
        "image_url": "https://myanimelist.net/images/anime/10/82594.jpg"
    },
    {
        "titre_affiche": "Koukaku Kidoutai",
        "titre_recherche": "Koukaku Kidoutai",
        "url_adkami": "https://www.adkami.com/anime/4314",
        "source": "Enigme_et_Policier",
        "score_mal": 8.27,
        "popularite_members": 701685,
        "image_url": "https://myanimelist.net/images/anime/10/82594.jpg"
    },
    {
        "titre_affiche": "Paprika",
        "titre_recherche": "Paprika",
        "url_adkami": "https://www.adkami.com/anime/278",
        "source": "Enigme_et_Policier",
        "score_mal": 8.04,
        "popularite_members": 610213,
        "image_url": "https://myanimelist.net/images/anime/1929/93629.jpg"
    },
    {
        "titre_affiche": "Paprika",
        "titre_recherche": "Paprika",
        "url_adkami": "https://www.adkami.com/anime/278",
        "source": "Enigme_et_Policier",
        "score_mal": 8.04,
        "popularite_members": 610213,
        "image_url": "https://myanimelist.net/images/anime/1929/93629.jpg"
    },
    {
        "titre_affiche": "Gosick",
        "titre_recherche": "Gosick",
        "url_adkami": "https://www.adkami.com/anime/47",
        "source": "Enigme_et_Policier",
        "score_mal": 8.04,
        "popularite_members": 602658,
        "image_url": "https://myanimelist.net/images/anime/11/27906.jpg"
    },
    {
        "titre_affiche": "Higurashi no Naku Koro ni Kai [Saison 2]",
        "titre_recherche": "Higurashi no Naku Koro ni Kai [Saison 2]",
        "url_adkami": "https://www.adkami.com/anime/326",
        "source": "Enigme_et_Policier",
        "score_mal": 8.16,
        "popularite_members": 519717,
        "image_url": "https://myanimelist.net/images/anime/12/14114.jpg"
    },
    {
        "titre_affiche": "Higurashi no Naku Koro ni Kai [Saison 2]",
        "titre_recherche": "Higurashi no Naku Koro ni Kai [Saison 2]",
        "url_adkami": "https://www.adkami.com/anime/326",
        "source": "Enigme_et_Policier",
        "score_mal": 8.16,
        "popularite_members": 519717,
        "image_url": "https://myanimelist.net/images/anime/12/14114.jpg"
    },
    {
        "titre_affiche": "Yuukoku no Moriarty",
        "titre_recherche": "Yuukoku no Moriarty",
        "url_adkami": "https://www.adkami.com/anime/3951",
        "source": "Enigme_et_Policier",
        "score_mal": 8.17,
        "popularite_members": 505569,
        "image_url": "https://myanimelist.net/images/anime/1464/108330.jpg"
    },
    {
        "titre_affiche": "Yuukoku no Moriarty",
        "titre_recherche": "Yuukoku no Moriarty",
        "url_adkami": "https://www.adkami.com/anime/3951",
        "source": "Enigme_et_Policier",
        "score_mal": 8.17,
        "popularite_members": 505569,
        "image_url": "https://myanimelist.net/images/anime/1464/108330.jpg"
    },
    {
        "titre_affiche": "Mousou Dairinin",
        "titre_recherche": "Mousou Dairinin",
        "url_adkami": "https://www.adkami.com/anime/159",
        "source": "Enigme_et_Policier",
        "score_mal": 7.66,
        "popularite_members": 473168,
        "image_url": "https://myanimelist.net/images/anime/7/10240.jpg"
    },
    {
        "titre_affiche": "Mousou Dairinin",
        "titre_recherche": "Mousou Dairinin",
        "url_adkami": "https://www.adkami.com/anime/159",
        "source": "Enigme_et_Policier",
        "score_mal": 7.66,
        "popularite_members": 473168,
        "image_url": "https://myanimelist.net/images/anime/7/10240.jpg"
    },
    {
        "titre_affiche": "Fugou Keiji: Balance:Unlimited",
        "titre_recherche": "Fugou Keiji: Balance:Unlimited",
        "url_adkami": "https://www.adkami.com/anime/3780",
        "source": "Enigme_et_Policier",
        "score_mal": 7.5,
        "popularite_members": 471231,
        "image_url": "https://myanimelist.net/images/anime/1066/106556.jpg"
    },
    {
        "titre_affiche": "Fugou Keiji: Balance:Unlimited",
        "titre_recherche": "Fugou Keiji: Balance:Unlimited",
        "url_adkami": "https://www.adkami.com/anime/3780",
        "source": "Enigme_et_Policier",
        "score_mal": 7.5,
        "popularite_members": 471231,
        "image_url": "https://myanimelist.net/images/anime/1066/106556.jpg"
    },
    {
        "titre_affiche": "Koukaku Kidoutai: Stand Alone Complex",
        "titre_recherche": "Koukaku Kidoutai: Stand Alone Complex",
        "url_adkami": "https://www.adkami.com/anime/1152",
        "source": "Enigme_et_Policier",
        "score_mal": 8.42,
        "popularite_members": 423585,
        "image_url": "https://myanimelist.net/images/anime/11/50857.jpg"
    },
    {
        "titre_affiche": "Koukaku Kidoutai: Stand Alone Complex",
        "titre_recherche": "Koukaku Kidoutai: Stand Alone Complex",
        "url_adkami": "https://www.adkami.com/anime/1152",
        "source": "Enigme_et_Policier",
        "score_mal": 8.42,
        "popularite_members": 423585,
        "image_url": "https://myanimelist.net/images/anime/11/50857.jpg"
    },
    {
        "titre_affiche": "Kemono Jihen",
        "titre_recherche": "Kemono Jihen",
        "url_adkami": "https://www.adkami.com/anime/4045",
        "source": "Enigme_et_Policier",
        "score_mal": 7.36,
        "popularite_members": 420277,
        "image_url": "https://myanimelist.net/images/anime/1258/108331.jpg"
    },
    {
        "titre_affiche": "Kemono Jihen",
        "titre_recherche": "Kemono Jihen",
        "url_adkami": "https://www.adkami.com/anime/4045",
        "source": "Enigme_et_Policier",
        "score_mal": 7.36,
        "popularite_members": 420277,
        "image_url": "https://myanimelist.net/images/anime/1258/108331.jpg"
    },
    {
        "titre_affiche": "Tantei wa mou, Shindeiru.",
        "titre_recherche": "Tantei wa mou, Shindeiru.",
        "url_adkami": "https://www.adkami.com/anime/4244",
        "source": "Enigme_et_Policier",
        "score_mal": 6.43,
        "popularite_members": 410724,
        "image_url": "https://myanimelist.net/images/anime/1843/115815.jpg"
    },
    {
        "titre_affiche": "Tantei wa mou, Shindeiru.",
        "titre_recherche": "Tantei wa mou, Shindeiru.",
        "url_adkami": "https://www.adkami.com/anime/4244",
        "source": "Enigme_et_Policier",
        "score_mal": 6.43,
        "popularite_members": 410724,
        "image_url": "https://myanimelist.net/images/anime/1843/115815.jpg"
    },
    {
        "titre_affiche": "Kaze Tachinu",
        "titre_recherche": "Kaze Tachinu",
        "url_adkami": "https://www.adkami.com/anime/3756",
        "source": "Enigme_et_Policier",
        "score_mal": 8.14,
        "popularite_members": 385594,
        "image_url": "https://myanimelist.net/images/anime/8/52353.jpg"
    },
    {
        "titre_affiche": "Kaze Tachinu",
        "titre_recherche": "Kaze Tachinu",
        "url_adkami": "https://www.adkami.com/anime/3756",
        "source": "Enigme_et_Policier",
        "score_mal": 8.14,
        "popularite_members": 385594,
        "image_url": "https://myanimelist.net/images/anime/8/52353.jpg"
    },
    {
        "titre_affiche": "Detective Conan",
        "titre_recherche": "Detective Conan",
        "url_adkami": "https://www.adkami.com/anime/7",
        "source": "Enigme_et_Policier",
        "score_mal": 8.18,
        "popularite_members": 377194,
        "image_url": "https://myanimelist.net/images/anime/7/75199.jpg"
    },
    {
        "titre_affiche": "Detective Conan",
        "titre_recherche": "Detective Conan",
        "url_adkami": "https://www.adkami.com/anime/7",
        "source": "Enigme_et_Policier",
        "score_mal": 8.18,
        "popularite_members": 377194,
        "image_url": "https://myanimelist.net/images/anime/7/75199.jpg"
    },
    {
        "titre_affiche": "B: The Beginning",
        "titre_recherche": "B: The Beginning",
        "url_adkami": "https://www.adkami.com/anime/2723",
        "source": "Enigme_et_Policier",
        "score_mal": 7.14,
        "popularite_members": 369905,
        "image_url": "https://myanimelist.net/images/anime/1564/90469.jpg"
    },
    {
        "titre_affiche": "B: The Beginning",
        "titre_recherche": "B: The Beginning",
        "url_adkami": "https://www.adkami.com/anime/2723",
        "source": "Enigme_et_Policier",
        "score_mal": 7.14,
        "popularite_members": 369905,
        "image_url": "https://myanimelist.net/images/anime/1564/90469.jpg"
    },
    {
        "titre_affiche": "Hamatora The Animation",
        "titre_recherche": "Hamatora The Animation",
        "url_adkami": "https://www.adkami.com/anime/1034",
        "source": "Enigme_et_Policier",
        "score_mal": 7.24,
        "popularite_members": 316333,
        "image_url": "https://myanimelist.net/images/anime/13/75653.jpg"
    },
    {
        "titre_affiche": "Hamatora The Animation",
        "titre_recherche": "Hamatora The Animation",
        "url_adkami": "https://www.adkami.com/anime/1034",
        "source": "Enigme_et_Policier",
        "score_mal": 7.24,
        "popularite_members": 316333,
        "image_url": "https://myanimelist.net/images/anime/13/75653.jpg"
    },
    {
        "titre_affiche": "Amnesia",
        "titre_recherche": "Amnesia",
        "url_adkami": "https://www.adkami.com/anime/432",
        "source": "Enigme_et_Policier",
        "score_mal": 5.97,
        "popularite_members": 309884,
        "image_url": "https://myanimelist.net/images/anime/1311/128738.jpg"
    },
    {
        "titre_affiche": "Amnesia",
        "titre_recherche": "Amnesia",
        "url_adkami": "https://www.adkami.com/anime/432",
        "source": "Enigme_et_Policier",
        "score_mal": 5.97,
        "popularite_members": 309884,
        "image_url": "https://myanimelist.net/images/anime/1311/128738.jpg"
    },
    {
        "titre_affiche": "Higurashi no Naku Koro ni Gou",
        "titre_recherche": "Higurashi no Naku Koro ni Gou",
        "url_adkami": "https://www.adkami.com/anime/3910",
        "source": "Enigme_et_Policier",
        "score_mal": 7.21,
        "popularite_members": 302857,
        "image_url": "https://myanimelist.net/images/anime/1716/111533.jpg"
    },
    {
        "titre_affiche": "Higurashi no Naku Koro ni Gou",
        "titre_recherche": "Higurashi no Naku Koro ni Gou",
        "url_adkami": "https://www.adkami.com/anime/3910",
        "source": "Enigme_et_Policier",
        "score_mal": 7.21,
        "popularite_members": 302857,
        "image_url": "https://myanimelist.net/images/anime/1716/111533.jpg"
    },
    {
        "titre_affiche": "Mirai Nikki",
        "titre_recherche": "Mirai Nikki",
        "url_adkami": "https://www.adkami.com/anime/130",
        "source": "Enigme_et_Policier",
        "score_mal": 7.18,
        "popularite_members": 254399,
        "image_url": "https://myanimelist.net/images/anime/10/22971.jpg"
    },
    {
        "titre_affiche": "Mirai Nikki",
        "titre_recherche": "Mirai Nikki",
        "url_adkami": "https://www.adkami.com/anime/130",
        "source": "Enigme_et_Policier",
        "score_mal": 7.18,
        "popularite_members": 254399,
        "image_url": "https://myanimelist.net/images/anime/10/22971.jpg"
    },
    {
        "titre_affiche": "Kamisama no Memochou",
        "titre_recherche": "Kamisama no Memochou",
        "url_adkami": "https://www.adkami.com/anime/394",
        "source": "Enigme_et_Policier",
        "score_mal": 7.46,
        "popularite_members": 249798,
        "image_url": "https://myanimelist.net/images/anime/13/75202.jpg"
    },
    {
        "titre_affiche": "Kamisama no Memochou",
        "titre_recherche": "Kamisama no Memochou",
        "url_adkami": "https://www.adkami.com/anime/394",
        "source": "Enigme_et_Policier",
        "score_mal": 7.46,
        "popularite_members": 249798,
        "image_url": "https://myanimelist.net/images/anime/13/75202.jpg"
    },
    {
        "titre_affiche": "Pluto",
        "titre_recherche": "Pluto",
        "url_adkami": "https://www.adkami.com/anime/5026",
        "source": "Enigme_et_Policier",
        "score_mal": 8.44,
        "popularite_members": 248725,
        "image_url": "https://myanimelist.net/images/anime/1021/138568.jpg"
    },
    {
        "titre_affiche": "Pluto",
        "titre_recherche": "Pluto",
        "url_adkami": "https://www.adkami.com/anime/5026",
        "source": "Enigme_et_Policier",
        "score_mal": 8.44,
        "popularite_members": 248725,
        "image_url": "https://myanimelist.net/images/anime/1021/138568.jpg"
    },
    {
        "titre_affiche": "Umineko no naku koro ni",
        "titre_recherche": "Umineko no naku koro ni",
        "url_adkami": "https://www.adkami.com/anime/523",
        "source": "Enigme_et_Policier",
        "score_mal": 7.03,
        "popularite_members": 234754,
        "image_url": "https://myanimelist.net/images/anime/10/17709.jpg"
    },
    {
        "titre_affiche": "Umineko no naku koro ni",
        "titre_recherche": "Umineko no naku koro ni",
        "url_adkami": "https://www.adkami.com/anime/523",
        "source": "Enigme_et_Policier",
        "score_mal": 7.03,
        "popularite_members": 234754,
        "image_url": "https://myanimelist.net/images/anime/10/17709.jpg"
    },
    {
        "titre_affiche": "Sakurako-san no Ashimoto ni wa Shitai ga Umatteiru",
        "titre_recherche": "Sakurako-san no Ashimoto ni wa Shitai ga Umatteiru",
        "url_adkami": "https://www.adkami.com/anime/1613",
        "source": "Enigme_et_Policier",
        "score_mal": 7.42,
        "popularite_members": 232218,
        "image_url": "https://myanimelist.net/images/anime/7/76116.jpg"
    },
    {
        "titre_affiche": "Sakurako-san no Ashimoto ni wa Shitai ga Umatteiru",
        "titre_recherche": "Sakurako-san no Ashimoto ni wa Shitai ga Umatteiru",
        "url_adkami": "https://www.adkami.com/anime/1613",
        "source": "Enigme_et_Policier",
        "score_mal": 7.42,
        "popularite_members": 232218,
        "image_url": "https://myanimelist.net/images/anime/7/76116.jpg"
    },
    {
        "titre_affiche": "Higurashi no Naku Koro ni Rei [OAV]",
        "titre_recherche": "Higurashi no Naku Koro ni Rei [OAV]",
        "url_adkami": "https://www.adkami.com/anime/327",
        "source": "Enigme_et_Policier",
        "score_mal": 7.41,
        "popularite_members": 206412,
        "image_url": "https://myanimelist.net/images/anime/4/14113.jpg"
    },
    {
        "titre_affiche": "Higurashi no Naku Koro ni Rei [OAV]",
        "titre_recherche": "Higurashi no Naku Koro ni Rei [OAV]",
        "url_adkami": "https://www.adkami.com/anime/327",
        "source": "Enigme_et_Policier",
        "score_mal": 7.41,
        "popularite_members": 206412,
        "image_url": "https://myanimelist.net/images/anime/4/14113.jpg"
    },
    {
        "titre_affiche": "Koroshi Ai",
        "titre_recherche": "Koroshi Ai",
        "url_adkami": "https://www.adkami.com/anime/4542",
        "source": "Enigme_et_Policier",
        "score_mal": 6.9,
        "popularite_members": 196090,
        "image_url": "https://myanimelist.net/images/anime/1485/119329.jpg"
    },
    {
        "titre_affiche": "Koroshi Ai",
        "titre_recherche": "Koroshi Ai",
        "url_adkami": "https://www.adkami.com/anime/4542",
        "source": "Enigme_et_Policier",
        "score_mal": 6.9,
        "popularite_members": 196090,
        "image_url": "https://myanimelist.net/images/anime/1485/119329.jpg"
    },
    {
        "titre_affiche": "Undead Girl Murder Farce",
        "titre_recherche": "Undead Girl Murder Farce",
        "url_adkami": "https://www.adkami.com/anime/4944",
        "source": "Enigme_et_Policier",
        "score_mal": 7.84,
        "popularite_members": 184043,
        "image_url": "https://myanimelist.net/images/anime/1946/136661.jpg"
    },
    {
        "titre_affiche": "Undead Girl Murder Farce",
        "titre_recherche": "Undead Girl Murder Farce",
        "url_adkami": "https://www.adkami.com/anime/4944",
        "source": "Enigme_et_Policier",
        "score_mal": 7.84,
        "popularite_members": 184043,
        "image_url": "https://myanimelist.net/images/anime/1946/136661.jpg"
    },
    {
        "titre_affiche": "Subete ga F ni Naru: The Perfect Insider",
        "titre_recherche": "Subete ga F ni Naru: The Perfect Insider",
        "url_adkami": "https://www.adkami.com/anime/1620",
        "source": "Enigme_et_Policier",
        "score_mal": 7.24,
        "popularite_members": 183277,
        "image_url": "https://myanimelist.net/images/anime/9/76071.jpg"
    },
    {
        "titre_affiche": "Subete ga F ni Naru: The Perfect Insider",
        "titre_recherche": "Subete ga F ni Naru: The Perfect Insider",
        "url_adkami": "https://www.adkami.com/anime/1620",
        "source": "Enigme_et_Policier",
        "score_mal": 7.24,
        "popularite_members": 183277,
        "image_url": "https://myanimelist.net/images/anime/9/76071.jpg"
    },
    {
        "titre_affiche": "Babylon",
        "titre_recherche": "Babylon",
        "url_adkami": "https://www.adkami.com/anime/3605",
        "source": "Enigme_et_Policier",
        "score_mal": 6.74,
        "popularite_members": 169495,
        "image_url": "https://myanimelist.net/images/anime/1942/102707.jpg"
    },
    {
        "titre_affiche": "Babylon",
        "titre_recherche": "Babylon",
        "url_adkami": "https://www.adkami.com/anime/3605",
        "source": "Enigme_et_Policier",
        "score_mal": 6.74,
        "popularite_members": 169495,
        "image_url": "https://myanimelist.net/images/anime/1942/102707.jpg"
    },
    {
        "titre_affiche": "Hakata Tonkotsu Ramens",
        "titre_recherche": "Hakata Tonkotsu Ramens",
        "url_adkami": "https://www.adkami.com/anime/2643",
        "source": "Enigme_et_Policier",
        "score_mal": 7.35,
        "popularite_members": 166173,
        "image_url": "https://myanimelist.net/images/anime/1718/91097.jpg"
    },
    {
        "titre_affiche": "Kamonohashi Ron no Kindan Suiri",
        "titre_recherche": "Kamonohashi Ron no Kindan Suiri",
        "url_adkami": "https://www.adkami.com/anime/4990",
        "source": "Enigme_et_Policier",
        "score_mal": 7.51,
        "popularite_members": 164975,
        "image_url": "https://myanimelist.net/images/anime/1799/137123.jpg"
    },
    {
        "titre_affiche": "Kamonohashi Ron no Kindan Suiri",
        "titre_recherche": "Kamonohashi Ron no Kindan Suiri",
        "url_adkami": "https://www.adkami.com/anime/4990",
        "source": "Enigme_et_Policier",
        "score_mal": 7.51,
        "popularite_members": 164975,
        "image_url": "https://myanimelist.net/images/anime/1799/137123.jpg"
    },
    {
        "titre_affiche": "Un-Go",
        "titre_recherche": "Un-Go",
        "url_adkami": "https://www.adkami.com/anime/419",
        "source": "Enigme_et_Policier",
        "score_mal": 7.33,
        "popularite_members": 159936,
        "image_url": "https://myanimelist.net/images/anime/1823/136763.jpg"
    },
    {
        "titre_affiche": "Un-Go",
        "titre_recherche": "Un-Go",
        "url_adkami": "https://www.adkami.com/anime/419",
        "source": "Enigme_et_Policier",
        "score_mal": 7.33,
        "popularite_members": 159936,
        "image_url": "https://myanimelist.net/images/anime/1823/136763.jpg"
    },
    {
        "titre_affiche": "Gyakuten Saiban: Sono \"Shinjitsu\", Igi Ari!",
        "titre_recherche": "Gyakuten Saiban: Sono \"Shinjitsu\", Igi Ari!",
        "url_adkami": "https://www.adkami.com/anime/1730",
        "source": "Enigme_et_Policier",
        "score_mal": 6.56,
        "popularite_members": 148613,
        "image_url": "https://myanimelist.net/images/anime/5/79448.jpg"
    },
    {
        "titre_affiche": "Gyakuten Saiban: Sono \"Shinjitsu\", Igi Ari!",
        "titre_recherche": "Gyakuten Saiban: Sono \"Shinjitsu\", Igi Ari!",
        "url_adkami": "https://www.adkami.com/anime/1730",
        "source": "Enigme_et_Policier",
        "score_mal": 6.56,
        "popularite_members": 148613,
        "image_url": "https://myanimelist.net/images/anime/5/79448.jpg"
    },
    {
        "titre_affiche": "Shinrei tantei yakumo",
        "titre_recherche": "Shinrei tantei yakumo",
        "url_adkami": "https://www.adkami.com/anime/258",
        "source": "Enigme_et_Policier",
        "score_mal": 7.3,
        "popularite_members": 139347,
        "image_url": "https://myanimelist.net/images/anime/13/35829.jpg"
    },
    {
        "titre_affiche": "Lupin III: Cagliostro no Shiro",
        "titre_recherche": "Lupin III: Cagliostro no Shiro",
        "url_adkami": "https://www.adkami.com/anime/2787",
        "source": "Enigme_et_Policier",
        "score_mal": 8.16,
        "popularite_members": 138552,
        "image_url": "https://myanimelist.net/images/anime/5/26182.jpg"
    },
    {
        "titre_affiche": "Lupin III: Cagliostro no Shiro",
        "titre_recherche": "Lupin III: Cagliostro no Shiro",
        "url_adkami": "https://www.adkami.com/anime/2787",
        "source": "Enigme_et_Policier",
        "score_mal": 8.16,
        "popularite_members": 138552,
        "image_url": "https://myanimelist.net/images/anime/5/26182.jpg"
    },
    {
        "titre_affiche": "Magic Kaito 1412",
        "titre_recherche": "Magic Kaito 1412",
        "url_adkami": "https://www.adkami.com/anime/1261",
        "source": "Enigme_et_Policier",
        "score_mal": 7.87,
        "popularite_members": 135545,
        "image_url": "https://myanimelist.net/images/anime/3/67807.jpg"
    },
    {
        "titre_affiche": "Witch Hunter Robin",
        "titre_recherche": "Witch Hunter Robin",
        "url_adkami": "https://www.adkami.com/anime/3124",
        "source": "Enigme_et_Policier",
        "score_mal": 7.25,
        "popularite_members": 129008,
        "image_url": "https://myanimelist.net/images/anime/10/19969.jpg"
    },
    {
        "titre_affiche": "Witch Hunter Robin",
        "titre_recherche": "Witch Hunter Robin",
        "url_adkami": "https://www.adkami.com/anime/3124",
        "source": "Enigme_et_Policier",
        "score_mal": 7.25,
        "popularite_members": 129008,
        "image_url": "https://myanimelist.net/images/anime/10/19969.jpg"
    },
    {
        "titre_affiche": "Ikebukuro West Gate Park",
        "titre_recherche": "Ikebukuro West Gate Park",
        "url_adkami": "https://www.adkami.com/anime/3936",
        "source": "Enigme_et_Policier",
        "score_mal": 6.87,
        "popularite_members": 128237,
        "image_url": "https://myanimelist.net/images/anime/1277/108376.jpg"
    },
    {
        "titre_affiche": "Ikebukuro West Gate Park",
        "titre_recherche": "Ikebukuro West Gate Park",
        "url_adkami": "https://www.adkami.com/anime/3936",
        "source": "Enigme_et_Policier",
        "score_mal": 6.87,
        "popularite_members": 128237,
        "image_url": "https://myanimelist.net/images/anime/1277/108376.jpg"
    },
    {
        "titre_affiche": "Cop Craft",
        "titre_recherche": "Cop Craft",
        "url_adkami": "https://www.adkami.com/anime/3497",
        "source": "Enigme_et_Policier",
        "score_mal": 6.72,
        "popularite_members": 128013,
        "image_url": "https://myanimelist.net/images/anime/1365/103219.jpg"
    },
    {
        "titre_affiche": "Cop Craft",
        "titre_recherche": "Cop Craft",
        "url_adkami": "https://www.adkami.com/anime/3497",
        "source": "Enigme_et_Policier",
        "score_mal": 6.72,
        "popularite_members": 128013,
        "image_url": "https://myanimelist.net/images/anime/1365/103219.jpg"
    },
    {
        "titre_affiche": "Ranpo Kitan : Game of Laplace",
        "titre_recherche": "Ranpo Kitan : Game of Laplace",
        "url_adkami": "https://www.adkami.com/anime/1514",
        "source": "Enigme_et_Policier",
        "score_mal": 6.57,
        "popularite_members": 126145,
        "image_url": "https://myanimelist.net/images/anime/5/79565.jpg"
    },
    {
        "titre_affiche": "Ranpo Kitan : Game of Laplace",
        "titre_recherche": "Ranpo Kitan : Game of Laplace",
        "url_adkami": "https://www.adkami.com/anime/1514",
        "source": "Enigme_et_Policier",
        "score_mal": 6.57,
        "popularite_members": 126145,
        "image_url": "https://myanimelist.net/images/anime/5/79565.jpg"
    },
    {
        "titre_affiche": "Psycho Pass : Sinners of the System",
        "titre_recherche": "Psycho Pass : Sinners of the System",
        "url_adkami": "https://www.adkami.com/anime/3600",
        "source": "Enigme_et_Policier",
        "score_mal": 7.16,
        "popularite_members": 124365,
        "image_url": "https://myanimelist.net/images/anime/1623/96878.jpg"
    },
    {
        "titre_affiche": "Psycho Pass : Sinners of the System",
        "titre_recherche": "Psycho Pass : Sinners of the System",
        "url_adkami": "https://www.adkami.com/anime/3600",
        "source": "Enigme_et_Policier",
        "score_mal": 7.16,
        "popularite_members": 124365,
        "image_url": "https://myanimelist.net/images/anime/1623/96878.jpg"
    },
    {
        "titre_affiche": "Trickster",
        "titre_recherche": "Trickster",
        "url_adkami": "https://www.adkami.com/anime/1896",
        "source": "Enigme_et_Policier",
        "score_mal": 6.26,
        "popularite_members": 121278,
        "image_url": "https://myanimelist.net/images/anime/9/81133.jpg"
    },
    {
        "titre_affiche": "Trickster",
        "titre_recherche": "Trickster",
        "url_adkami": "https://www.adkami.com/anime/1896",
        "source": "Enigme_et_Policier",
        "score_mal": 6.26,
        "popularite_members": 121278,
        "image_url": "https://myanimelist.net/images/anime/9/81133.jpg"
    },
    {
        "titre_affiche": "Yami Shibai",
        "titre_recherche": "Yami Shibai",
        "url_adkami": "https://www.adkami.com/anime/1246",
        "source": "Enigme_et_Policier",
        "score_mal": 6.99,
        "popularite_members": 117321,
        "image_url": "https://myanimelist.net/images/anime/11/51995.jpg"
    },
    {
        "titre_affiche": "Yami Shibai",
        "titre_recherche": "Yami Shibai",
        "url_adkami": "https://www.adkami.com/anime/1246",
        "source": "Enigme_et_Policier",
        "score_mal": 6.99,
        "popularite_members": 117321,
        "image_url": "https://myanimelist.net/images/anime/11/51995.jpg"
    },
    {
        "titre_affiche": "Cuticle Detective Inaba",
        "titre_recherche": "Cuticle Detective Inaba",
        "url_adkami": "https://www.adkami.com/anime/427",
        "source": "Enigme_et_Policier",
        "score_mal": 7.24,
        "popularite_members": 115015,
        "image_url": "https://myanimelist.net/images/anime/10/73934.jpg"
    },
    {
        "titre_affiche": "Cuticle Detective Inaba",
        "titre_recherche": "Cuticle Detective Inaba",
        "url_adkami": "https://www.adkami.com/anime/427",
        "source": "Enigme_et_Policier",
        "score_mal": 7.24,
        "popularite_members": 115015,
        "image_url": "https://myanimelist.net/images/anime/10/73934.jpg"
    },
    {
        "titre_affiche": "Phi Brain: Kami no Puzzle",
        "titre_recherche": "Phi Brain: Kami no Puzzle",
        "url_adkami": "https://www.adkami.com/anime/21",
        "source": "Enigme_et_Policier",
        "score_mal": 7.16,
        "popularite_members": 113493,
        "image_url": "https://myanimelist.net/images/anime/12/34045.jpg"
    },
    {
        "titre_affiche": "Phi Brain: Kami no Puzzle",
        "titre_recherche": "Phi Brain: Kami no Puzzle",
        "url_adkami": "https://www.adkami.com/anime/21",
        "source": "Enigme_et_Policier",
        "score_mal": 7.16,
        "popularite_members": 113493,
        "image_url": "https://myanimelist.net/images/anime/12/34045.jpg"
    },
    {
        "titre_affiche": "Seikaisuru Kado",
        "titre_recherche": "Seikaisuru Kado",
        "url_adkami": "https://www.adkami.com/anime/2196",
        "source": "Enigme_et_Policier",
        "score_mal": 6.72,
        "popularite_members": 111756,
        "image_url": "https://myanimelist.net/images/anime/3/85255.jpg"
    },
    {
        "titre_affiche": "Seikaisuru Kado",
        "titre_recherche": "Seikaisuru Kado",
        "url_adkami": "https://www.adkami.com/anime/2196",
        "source": "Enigme_et_Policier",
        "score_mal": 6.72,
        "popularite_members": 111756,
        "image_url": "https://myanimelist.net/images/anime/3/85255.jpg"
    },
    {
        "titre_affiche": "Persona 4 The Golden Animation",
        "titre_recherche": "Persona 4 The Golden Animation",
        "url_adkami": "https://www.adkami.com/anime/1187",
        "source": "Enigme_et_Policier",
        "score_mal": 6.65,
        "popularite_members": 102254,
        "image_url": "https://myanimelist.net/images/anime/3/63251.jpg"
    },
    {
        "titre_affiche": "Persona 4 The Golden Animation",
        "titre_recherche": "Persona 4 The Golden Animation",
        "url_adkami": "https://www.adkami.com/anime/1187",
        "source": "Enigme_et_Policier",
        "score_mal": 6.65,
        "popularite_members": 102254,
        "image_url": "https://myanimelist.net/images/anime/3/63251.jpg"
    },
    {
        "titre_affiche": "Ameku Takao no Suiri Karte",
        "titre_recherche": "Ameku Takao no Suiri Karte",
        "url_adkami": "https://www.adkami.com/anime/5345",
        "source": "Enigme_et_Policier",
        "score_mal": 7.14,
        "popularite_members": 98397,
        "image_url": "https://myanimelist.net/images/anime/1096/147327.jpg"
    },
    {
        "titre_affiche": "Ameku Takao no Suiri Karte",
        "titre_recherche": "Ameku Takao no Suiri Karte",
        "url_adkami": "https://www.adkami.com/anime/5345",
        "source": "Enigme_et_Policier",
        "score_mal": 7.14,
        "popularite_members": 98397,
        "image_url": "https://myanimelist.net/images/anime/1096/147327.jpg"
    },
    {
        "titre_affiche": "HaruChika: Haruta to Chika wa Seishun suru",
        "titre_recherche": "HaruChika: Haruta to Chika wa Seishun suru",
        "url_adkami": "https://www.adkami.com/anime/1674",
        "source": "Enigme_et_Policier",
        "score_mal": 6.33,
        "popularite_members": 97991,
        "image_url": "https://myanimelist.net/images/anime/6/77835.jpg"
    },
    {
        "titre_affiche": "HaruChika: Haruta to Chika wa Seishun suru",
        "titre_recherche": "HaruChika: Haruta to Chika wa Seishun suru",
        "url_adkami": "https://www.adkami.com/anime/1674",
        "source": "Enigme_et_Policier",
        "score_mal": 6.33,
        "popularite_members": 97991,
        "image_url": "https://myanimelist.net/images/anime/6/77835.jpg"
    },
    {
        "titre_affiche": "Higurashi no Naku Koro ni Kira [OAV 2nd]",
        "titre_recherche": "Higurashi no Naku Koro ni Kira [OAV 2nd]",
        "url_adkami": "https://www.adkami.com/anime/328",
        "source": "Enigme_et_Policier",
        "score_mal": 6.56,
        "popularite_members": 91729,
        "image_url": "https://myanimelist.net/images/anime/6/29774.jpg"
    },
    {
        "titre_affiche": "Higurashi no Naku Koro ni Kira [OAV 2nd]",
        "titre_recherche": "Higurashi no Naku Koro ni Kira [OAV 2nd]",
        "url_adkami": "https://www.adkami.com/anime/328",
        "source": "Enigme_et_Policier",
        "score_mal": 6.56,
        "popularite_members": 91729,
        "image_url": "https://myanimelist.net/images/anime/6/29774.jpg"
    },
    {
        "titre_affiche": "Kabukichou Sherlock",
        "titre_recherche": "Kabukichou Sherlock",
        "url_adkami": "https://www.adkami.com/anime/3611",
        "source": "Enigme_et_Policier",
        "score_mal": 6.9,
        "popularite_members": 87448,
        "image_url": "https://myanimelist.net/images/anime/1657/111622.jpg"
    },
    {
        "titre_affiche": "Kabukichou Sherlock",
        "titre_recherche": "Kabukichou Sherlock",
        "url_adkami": "https://www.adkami.com/anime/3611",
        "source": "Enigme_et_Policier",
        "score_mal": 6.9,
        "popularite_members": 87448,
        "image_url": "https://myanimelist.net/images/anime/1657/111622.jpg"
    },
    {
        "titre_affiche": "Grisaia: Phantom Trigger The Animation",
        "titre_recherche": "Grisaia: Phantom Trigger The Animation",
        "url_adkami": "https://www.adkami.com/anime/3385",
        "source": "Enigme_et_Policier",
        "score_mal": 6.88,
        "popularite_members": 84759,
        "image_url": "https://myanimelist.net/images/anime/1275/97358.jpg"
    },
    {
        "titre_affiche": "Grisaia: Phantom Trigger The Animation",
        "titre_recherche": "Grisaia: Phantom Trigger The Animation",
        "url_adkami": "https://www.adkami.com/anime/3385",
        "source": "Enigme_et_Policier",
        "score_mal": 6.88,
        "popularite_members": 84759,
        "image_url": "https://myanimelist.net/images/anime/1275/97358.jpg"
    },
    {
        "titre_affiche": "Higurashi no Naku Koro ni Special : Nekogoroshi-Hen",
        "titre_recherche": "Higurashi no Naku Koro ni Special : Nekogoroshi-Hen",
        "url_adkami": "https://www.adkami.com/anime/1146",
        "source": "Enigme_et_Policier",
        "score_mal": 7.13,
        "popularite_members": 82570,
        "image_url": "https://myanimelist.net/images/anime/1492/118476.jpg"
    },
    {
        "titre_affiche": "Higurashi no Naku Koro ni Special : Nekogoroshi-Hen",
        "titre_recherche": "Higurashi no Naku Koro ni Special : Nekogoroshi-Hen",
        "url_adkami": "https://www.adkami.com/anime/1146",
        "source": "Enigme_et_Policier",
        "score_mal": 7.13,
        "popularite_members": 82570,
        "image_url": "https://myanimelist.net/images/anime/1492/118476.jpg"
    },
    {
        "titre_affiche": "Mayonaka no Occult Koumuin",
        "titre_recherche": "Mayonaka no Occult Koumuin",
        "url_adkami": "https://www.adkami.com/anime/3350",
        "source": "Enigme_et_Policier",
        "score_mal": 6.78,
        "popularite_members": 80436,
        "image_url": "https://myanimelist.net/images/anime/1859/100448.jpg"
    },
    {
        "titre_affiche": "Mayonaka no Occult Koumuin",
        "titre_recherche": "Mayonaka no Occult Koumuin",
        "url_adkami": "https://www.adkami.com/anime/3350",
        "source": "Enigme_et_Policier",
        "score_mal": 6.78,
        "popularite_members": 80436,
        "image_url": "https://myanimelist.net/images/anime/1859/100448.jpg"
    },
    {
        "titre_affiche": "Magic Kaito",
        "titre_recherche": "Magic Kaito",
        "url_adkami": "https://www.adkami.com/anime/52",
        "source": "Enigme_et_Policier",
        "score_mal": 7.78,
        "popularite_members": 78838,
        "image_url": "https://myanimelist.net/images/anime/1946/149930.jpg"
    },
    {
        "titre_affiche": "Fuuto Pi",
        "titre_recherche": "Fuuto Pi",
        "url_adkami": "https://www.adkami.com/anime/4690",
        "source": "Enigme_et_Policier",
        "score_mal": 7.33,
        "popularite_members": 78141,
        "image_url": "https://myanimelist.net/images/anime/1945/123588.jpg"
    },
    {
        "titre_affiche": "Fuuto Pi",
        "titre_recherche": "Fuuto Pi",
        "url_adkami": "https://www.adkami.com/anime/4690",
        "source": "Enigme_et_Policier",
        "score_mal": 7.33,
        "popularite_members": 78141,
        "image_url": "https://myanimelist.net/images/anime/1945/123588.jpg"
    },
    {
        "titre_affiche": "Lupin III: Part 4",
        "titre_recherche": "Lupin III: Part 4",
        "url_adkami": "https://www.adkami.com/anime/1602",
        "source": "Enigme_et_Policier",
        "score_mal": 7.91,
        "popularite_members": 77950,
        "image_url": "https://myanimelist.net/images/anime/9/75949.jpg"
    },
    {
        "titre_affiche": "Lupin III: Part 4",
        "titre_recherche": "Lupin III: Part 4",
        "url_adkami": "https://www.adkami.com/anime/1602",
        "source": "Enigme_et_Policier",
        "score_mal": 7.91,
        "popularite_members": 77950,
        "image_url": "https://myanimelist.net/images/anime/9/75949.jpg"
    },
    {
        "titre_affiche": "Higurashi no Naku Koro ni Kaku",
        "titre_recherche": "Higurashi no Naku Koro ni Kaku",
        "url_adkami": "https://www.adkami.com/anime/1140",
        "source": "Enigme_et_Policier",
        "score_mal": 7.21,
        "popularite_members": 75425,
        "image_url": "https://myanimelist.net/images/anime/12/51063.jpg"
    },
    {
        "titre_affiche": "Higurashi no Naku Koro ni Kaku",
        "titre_recherche": "Higurashi no Naku Koro ni Kaku",
        "url_adkami": "https://www.adkami.com/anime/1140",
        "source": "Enigme_et_Policier",
        "score_mal": 7.21,
        "popularite_members": 75425,
        "image_url": "https://myanimelist.net/images/anime/12/51063.jpg"
    },
    {
        "titre_affiche": "Gunsmith Cats",
        "titre_recherche": "Gunsmith Cats",
        "url_adkami": "https://www.adkami.com/anime/3330",
        "source": "Enigme_et_Policier",
        "score_mal": 7.43,
        "popularite_members": 74127,
        "image_url": "https://myanimelist.net/images/anime/1461/152457.jpg"
    },
    {
        "titre_affiche": "Gunsmith Cats",
        "titre_recherche": "Gunsmith Cats",
        "url_adkami": "https://www.adkami.com/anime/3330",
        "source": "Enigme_et_Policier",
        "score_mal": 7.43,
        "popularite_members": 74127,
        "image_url": "https://myanimelist.net/images/anime/1461/152457.jpg"
    },
    {
        "titre_affiche": "Henjin no Salad Bowl",
        "titre_recherche": "Henjin no Salad Bowl",
        "url_adkami": "https://www.adkami.com/anime/5146",
        "source": "Enigme_et_Policier",
        "score_mal": 7.28,
        "popularite_members": 72287,
        "image_url": "https://myanimelist.net/images/anime/1861/141482.jpg"
    },
    {
        "titre_affiche": "Henjin no Salad Bowl",
        "titre_recherche": "Henjin no Salad Bowl",
        "url_adkami": "https://www.adkami.com/anime/5146",
        "source": "Enigme_et_Policier",
        "score_mal": 7.28,
        "popularite_members": 72287,
        "image_url": "https://myanimelist.net/images/anime/1861/141482.jpg"
    },
    {
        "titre_affiche": "Majin Tantei Nougami Neuro",
        "titre_recherche": "Majin Tantei Nougami Neuro",
        "url_adkami": "https://www.adkami.com/anime/994",
        "source": "Enigme_et_Policier",
        "score_mal": 7.59,
        "popularite_members": 71682,
        "image_url": "https://myanimelist.net/images/anime/12/20930.jpg"
    },
    {
        "titre_affiche": "Majin Tantei Nougami Neuro",
        "titre_recherche": "Majin Tantei Nougami Neuro",
        "url_adkami": "https://www.adkami.com/anime/994",
        "source": "Enigme_et_Policier",
        "score_mal": 7.59,
        "popularite_members": 71682,
        "image_url": "https://myanimelist.net/images/anime/12/20930.jpg"
    },
    {
        "titre_affiche": "Kyoto Teramachi Sanjou no Holmes",
        "titre_recherche": "Kyoto Teramachi Sanjou no Holmes",
        "url_adkami": "https://www.adkami.com/anime/2967",
        "source": "Enigme_et_Policier",
        "score_mal": 6.75,
        "popularite_members": 70054,
        "image_url": "https://myanimelist.net/images/anime/1304/92930.jpg"
    },
    {
        "titre_affiche": "Kyoto Teramachi Sanjou no Holmes",
        "titre_recherche": "Kyoto Teramachi Sanjou no Holmes",
        "url_adkami": "https://www.adkami.com/anime/2967",
        "source": "Enigme_et_Policier",
        "score_mal": 6.75,
        "popularite_members": 70054,
        "image_url": "https://myanimelist.net/images/anime/1304/92930.jpg"
    },
    {
        "titre_affiche": "Imawa no Kuni no Alice",
        "titre_recherche": "Imawa no Kuni no Alice",
        "url_adkami": "https://www.adkami.com/anime/1307",
        "source": "Enigme_et_Policier",
        "score_mal": 7.25,
        "popularite_members": 69747,
        "image_url": "https://myanimelist.net/images/anime/1004/96669.jpg"
    },
    {
        "titre_affiche": "Imawa no Kuni no Alice",
        "titre_recherche": "Imawa no Kuni no Alice",
        "url_adkami": "https://www.adkami.com/anime/1307",
        "source": "Enigme_et_Policier",
        "score_mal": 7.25,
        "popularite_members": 69747,
        "image_url": "https://myanimelist.net/images/anime/1004/96669.jpg"
    },
    {
        "titre_affiche": "Mouryou no Hako",
        "titre_recherche": "Mouryou no Hako",
        "url_adkami": "https://www.adkami.com/anime/816",
        "source": "Enigme_et_Policier",
        "score_mal": 7.16,
        "popularite_members": 67681,
        "image_url": "https://myanimelist.net/images/anime/10/75492.jpg"
    },
    {
        "titre_affiche": "Ninja Batman",
        "titre_recherche": "Ninja Batman",
        "url_adkami": "https://www.adkami.com/anime/2914",
        "source": "Enigme_et_Policier",
        "score_mal": 6.11,
        "popularite_members": 64986,
        "image_url": "https://myanimelist.net/images/anime/1351/95947.jpg"
    },
    {
        "titre_affiche": "Active Raid",
        "titre_recherche": "Active Raid",
        "url_adkami": "https://www.adkami.com/anime/1675",
        "source": "Enigme_et_Policier",
        "score_mal": 5.87,
        "popularite_members": 61408,
        "image_url": "https://myanimelist.net/images/anime/3/77977.jpg"
    },
    {
        "titre_affiche": "Active Raid",
        "titre_recherche": "Active Raid",
        "url_adkami": "https://www.adkami.com/anime/1675",
        "source": "Enigme_et_Policier",
        "score_mal": 5.87,
        "popularite_members": 61408,
        "image_url": "https://myanimelist.net/images/anime/3/77977.jpg"
    },
    {
        "titre_affiche": "18 If",
        "titre_recherche": "18 If",
        "url_adkami": "https://www.adkami.com/anime/2372",
        "source": "Enigme_et_Policier",
        "score_mal": 6.12,
        "popularite_members": 60447,
        "image_url": "https://myanimelist.net/images/anime/7/86743.jpg"
    },
    {
        "titre_affiche": "El Cazador de la Bruja",
        "titre_recherche": "El Cazador de la Bruja",
        "url_adkami": "https://www.adkami.com/anime/1350",
        "source": "Enigme_et_Policier",
        "score_mal": 7.24,
        "popularite_members": 59754,
        "image_url": "https://myanimelist.net/images/anime/1446/98891.jpg"
    },
    {
        "titre_affiche": "El Cazador de la Bruja",
        "titre_recherche": "El Cazador de la Bruja",
        "url_adkami": "https://www.adkami.com/anime/1350",
        "source": "Enigme_et_Policier",
        "score_mal": 7.24,
        "popularite_members": 59754,
        "image_url": "https://myanimelist.net/images/anime/1446/98891.jpg"
    },
    {
        "titre_affiche": "Bungou to Alchemist: Shinpan no Haguruma",
        "titre_recherche": "Bungou to Alchemist: Shinpan no Haguruma",
        "url_adkami": "https://www.adkami.com/anime/3789",
        "source": "Enigme_et_Policier",
        "score_mal": 6.54,
        "popularite_members": 58691,
        "image_url": "https://myanimelist.net/images/anime/1223/114346.jpg"
    },
    {
        "titre_affiche": "Bungou to Alchemist: Shinpan no Haguruma",
        "titre_recherche": "Bungou to Alchemist: Shinpan no Haguruma",
        "url_adkami": "https://www.adkami.com/anime/3789",
        "source": "Enigme_et_Policier",
        "score_mal": 6.54,
        "popularite_members": 58691,
        "image_url": "https://myanimelist.net/images/anime/1223/114346.jpg"
    },
    {
        "titre_affiche": "Hakozume: Kouban Joshi no Gyakushuu",
        "titre_recherche": "Hakozume: Kouban Joshi no Gyakushuu",
        "url_adkami": "https://www.adkami.com/anime/4518",
        "source": "Enigme_et_Policier",
        "score_mal": 7.17,
        "popularite_members": 58154,
        "image_url": "https://myanimelist.net/images/anime/1302/119917.jpg"
    },
    {
        "titre_affiche": "Hakozume: Kouban Joshi no Gyakushuu",
        "titre_recherche": "Hakozume: Kouban Joshi no Gyakushuu",
        "url_adkami": "https://www.adkami.com/anime/4518",
        "source": "Enigme_et_Policier",
        "score_mal": 7.17,
        "popularite_members": 58154,
        "image_url": "https://myanimelist.net/images/anime/1302/119917.jpg"
    },
    {
        "titre_affiche": "Spiral: Suiri no Kizuna",
        "titre_recherche": "Spiral: Suiri no Kizuna",
        "url_adkami": "https://www.adkami.com/anime/1372",
        "source": "Enigme_et_Policier",
        "score_mal": 7.22,
        "popularite_members": 55348,
        "image_url": "https://myanimelist.net/images/anime/1771/92118.jpg"
    },
    {
        "titre_affiche": "Keishichou Tokumu Bu Tokushu Kyouakuhan Taisaku Shitsu Dai Nana Ka : Tokunana",
        "titre_recherche": "Keishichou Tokumu Bu Tokushu Kyouakuhan Taisaku Shitsu Dai Nana Ka : Tokunana",
        "url_adkami": "https://www.adkami.com/anime/3599",
        "source": "Enigme_et_Policier",
        "score_mal": 6.09,
        "popularite_members": 51500,
        "image_url": "https://myanimelist.net/images/anime/1556/111623.jpg"
    },
    {
        "titre_affiche": "Keishichou Tokumu Bu Tokushu Kyouakuhan Taisaku Shitsu Dai Nana Ka : Tokunana",
        "titre_recherche": "Keishichou Tokumu Bu Tokushu Kyouakuhan Taisaku Shitsu Dai Nana Ka : Tokunana",
        "url_adkami": "https://www.adkami.com/anime/3599",
        "source": "Enigme_et_Policier",
        "score_mal": 6.09,
        "popularite_members": 51500,
        "image_url": "https://myanimelist.net/images/anime/1556/111623.jpg"
    },
    {
        "titre_affiche": "Hana to Alice : Satsujin Jiken",
        "titre_recherche": "Hana to Alice : Satsujin Jiken",
        "url_adkami": "https://www.adkami.com/anime/3571",
        "source": "Enigme_et_Policier",
        "score_mal": 7.26,
        "popularite_members": 50808,
        "image_url": "https://myanimelist.net/images/anime/12/71197.jpg"
    },
    {
        "titre_affiche": "Hana to Alice : Satsujin Jiken",
        "titre_recherche": "Hana to Alice : Satsujin Jiken",
        "url_adkami": "https://www.adkami.com/anime/3571",
        "source": "Enigme_et_Policier",
        "score_mal": 7.26,
        "popularite_members": 50808,
        "image_url": "https://myanimelist.net/images/anime/12/71197.jpg"
    },
    {
        "titre_affiche": "Gnosia",
        "titre_recherche": "Gnosia",
        "url_adkami": "https://www.adkami.com/anime/5852",
        "source": "Enigme_et_Policier",
        "score_mal": 7.87,
        "popularite_members": 50106,
        "image_url": "https://myanimelist.net/images/anime/1257/152352.jpg"
    },
    {
        "titre_affiche": "Gnosia",
        "titre_recherche": "Gnosia",
        "url_adkami": "https://www.adkami.com/anime/5852",
        "source": "Enigme_et_Policier",
        "score_mal": 7.87,
        "popularite_members": 50106,
        "image_url": "https://myanimelist.net/images/anime/1257/152352.jpg"
    },
    {
        "titre_affiche": "Mattaku Saikin no Tantei to Kitara",
        "titre_recherche": "Mattaku Saikin no Tantei to Kitara",
        "url_adkami": "https://www.adkami.com/anime/5736",
        "source": "Enigme_et_Policier",
        "score_mal": 7.35,
        "popularite_members": 49587,
        "image_url": "https://myanimelist.net/images/anime/1323/149460.jpg"
    },
    {
        "titre_affiche": "Mattaku Saikin no Tantei to Kitara",
        "titre_recherche": "Mattaku Saikin no Tantei to Kitara",
        "url_adkami": "https://www.adkami.com/anime/5736",
        "source": "Enigme_et_Policier",
        "score_mal": 7.35,
        "popularite_members": 49587,
        "image_url": "https://myanimelist.net/images/anime/1323/149460.jpg"
    },
    {
        "titre_affiche": "Lupin III: Part 5",
        "titre_recherche": "Lupin III: Part 5",
        "url_adkami": "https://www.adkami.com/anime/2886",
        "source": "Enigme_et_Policier",
        "score_mal": 8.14,
        "popularite_members": 49034,
        "image_url": "https://myanimelist.net/images/anime/1235/91028.jpg"
    },
    {
        "titre_affiche": "Lupin III: Part 5",
        "titre_recherche": "Lupin III: Part 5",
        "url_adkami": "https://www.adkami.com/anime/2886",
        "source": "Enigme_et_Policier",
        "score_mal": 8.14,
        "popularite_members": 49034,
        "image_url": "https://myanimelist.net/images/anime/1235/91028.jpg"
    },
    {
        "titre_affiche": "Lupin III: The First",
        "titre_recherche": "Lupin III: The First",
        "url_adkami": "https://www.adkami.com/anime/4075",
        "source": "Enigme_et_Policier",
        "score_mal": 7.81,
        "popularite_members": 48409,
        "image_url": "https://myanimelist.net/images/anime/1572/108506.jpg"
    },
    {
        "titre_affiche": "Lupin III: The First",
        "titre_recherche": "Lupin III: The First",
        "url_adkami": "https://www.adkami.com/anime/4075",
        "source": "Enigme_et_Policier",
        "score_mal": 7.81,
        "popularite_members": 48409,
        "image_url": "https://myanimelist.net/images/anime/1572/108506.jpg"
    },
    {
        "titre_affiche": "Tantei Opera Milky Holmes",
        "titre_recherche": "Tantei Opera Milky Holmes",
        "url_adkami": "https://www.adkami.com/anime/813",
        "source": "Enigme_et_Policier",
        "score_mal": 6.95,
        "popularite_members": 48363,
        "image_url": "https://myanimelist.net/images/anime/10/26676.jpg"
    },
    {
        "titre_affiche": "Kidou Keisatsu Patlabor: On Television",
        "titre_recherche": "Kidou Keisatsu Patlabor: On Television",
        "url_adkami": "https://www.adkami.com/anime/3401",
        "source": "Enigme_et_Policier",
        "score_mal": 7.74,
        "popularite_members": 46551,
        "image_url": "https://myanimelist.net/images/anime/1739/144310.jpg"
    },
    {
        "titre_affiche": "Kidou Keisatsu Patlabor: On Television",
        "titre_recherche": "Kidou Keisatsu Patlabor: On Television",
        "url_adkami": "https://www.adkami.com/anime/3401",
        "source": "Enigme_et_Policier",
        "score_mal": 7.74,
        "popularite_members": 46551,
        "image_url": "https://myanimelist.net/images/anime/1739/144310.jpg"
    },
    {
        "titre_affiche": "Koukaku Kidoutai Arise: Alternative Architecture",
        "titre_recherche": "Koukaku Kidoutai Arise: Alternative Architecture",
        "url_adkami": "https://www.adkami.com/anime/1436",
        "source": "Enigme_et_Policier",
        "score_mal": 7.21,
        "popularite_members": 46180,
        "image_url": "https://myanimelist.net/images/anime/5/72037.jpg"
    },
    {
        "titre_affiche": "Koukaku Kidoutai Arise: Alternative Architecture",
        "titre_recherche": "Koukaku Kidoutai Arise: Alternative Architecture",
        "url_adkami": "https://www.adkami.com/anime/1436",
        "source": "Enigme_et_Policier",
        "score_mal": 7.21,
        "popularite_members": 46180,
        "image_url": "https://myanimelist.net/images/anime/5/72037.jpg"
    },
    {
        "titre_affiche": "Touhou Musou Kakyou a Summer Day\\'s Dream",
        "titre_recherche": "Touhou Musou Kakyou a Summer Day\\'s Dream",
        "url_adkami": "https://www.adkami.com/anime/1217",
        "source": "Enigme_et_Policier",
        "score_mal": 7.3,
        "popularite_members": 43108,
        "image_url": "https://myanimelist.net/images/anime/3/27302.jpg"
    },
    {
        "titre_affiche": "Your Forma",
        "titre_recherche": "Your Forma",
        "url_adkami": "https://www.adkami.com/anime/5538",
        "source": "Enigme_et_Policier",
        "score_mal": 6.27,
        "popularite_members": 42957,
        "image_url": "https://myanimelist.net/images/anime/1577/147967.jpg"
    },
    {
        "titre_affiche": "Your Forma",
        "titre_recherche": "Your Forma",
        "url_adkami": "https://www.adkami.com/anime/5538",
        "source": "Enigme_et_Policier",
        "score_mal": 6.27,
        "popularite_members": 42957,
        "image_url": "https://myanimelist.net/images/anime/1577/147967.jpg"
    },
    {
        "titre_affiche": "Matantei Loki Ragnarok",
        "titre_recherche": "Matantei Loki Ragnarok",
        "url_adkami": "https://www.adkami.com/anime/1094",
        "source": "Enigme_et_Policier",
        "score_mal": 7.27,
        "popularite_members": 41343,
        "image_url": "https://myanimelist.net/images/anime/13/75300.jpg"
    },
    {
        "titre_affiche": "Cyber City Oedo 808",
        "titre_recherche": "Cyber City Oedo 808",
        "url_adkami": "https://www.adkami.com/anime/3413",
        "source": "Enigme_et_Policier",
        "score_mal": 7.25,
        "popularite_members": 37810,
        "image_url": "https://myanimelist.net/images/anime/8/58763.jpg"
    },
    {
        "titre_affiche": "Cyber City Oedo 808",
        "titre_recherche": "Cyber City Oedo 808",
        "url_adkami": "https://www.adkami.com/anime/3413",
        "source": "Enigme_et_Policier",
        "score_mal": 7.25,
        "popularite_members": 37810,
        "image_url": "https://myanimelist.net/images/anime/8/58763.jpg"
    },
    {
        "titre_affiche": "Nijuu Mensou no Musume",
        "titre_recherche": "Nijuu Mensou no Musume",
        "url_adkami": "https://www.adkami.com/anime/4716",
        "source": "Enigme_et_Policier",
        "score_mal": 7.56,
        "popularite_members": 36992,
        "image_url": "https://myanimelist.net/images/anime/3/8694.jpg"
    },
    {
        "titre_affiche": "Nijuu Mensou no Musume",
        "titre_recherche": "Nijuu Mensou no Musume",
        "url_adkami": "https://www.adkami.com/anime/4716",
        "source": "Enigme_et_Policier",
        "score_mal": 7.56,
        "popularite_members": 36992,
        "image_url": "https://myanimelist.net/images/anime/3/8694.jpg"
    },
    {
        "titre_affiche": "Lupin III vs. Detective Conan: The Movie",
        "titre_recherche": "Lupin III vs. Detective Conan: The Movie",
        "url_adkami": "https://www.adkami.com/anime/1160",
        "source": "Enigme_et_Policier",
        "score_mal": 7.86,
        "popularite_members": 36897,
        "image_url": "https://myanimelist.net/images/anime/4/51663.jpg"
    },
    {
        "titre_affiche": "Lupin III vs. Detective Conan: The Movie",
        "titre_recherche": "Lupin III vs. Detective Conan: The Movie",
        "url_adkami": "https://www.adkami.com/anime/1160",
        "source": "Enigme_et_Policier",
        "score_mal": 7.86,
        "popularite_members": 36897,
        "image_url": "https://myanimelist.net/images/anime/4/51663.jpg"
    },
    {
        "titre_affiche": "Kindaichi Shounen no Jikenbo",
        "titre_recherche": "Kindaichi Shounen no Jikenbo",
        "url_adkami": "https://www.adkami.com/anime/451",
        "source": "Enigme_et_Policier",
        "score_mal": 7.98,
        "popularite_members": 36439,
        "image_url": "https://myanimelist.net/images/anime/1702/120440.jpg"
    },
    {
        "titre_affiche": "Kindaichi Shounen no Jikenbo",
        "titre_recherche": "Kindaichi Shounen no Jikenbo",
        "url_adkami": "https://www.adkami.com/anime/451",
        "source": "Enigme_et_Policier",
        "score_mal": 7.98,
        "popularite_members": 36439,
        "image_url": "https://myanimelist.net/images/anime/1702/120440.jpg"
    },
    {
        "titre_affiche": "Taiho Shichau zo",
        "titre_recherche": "Taiho Shichau zo",
        "url_adkami": "https://www.adkami.com/anime/3755",
        "source": "Enigme_et_Policier",
        "score_mal": 7.53,
        "popularite_members": 36179,
        "image_url": "https://myanimelist.net/images/anime/1498/97153.jpg"
    },
    {
        "titre_affiche": "Taiho Shichau zo",
        "titre_recherche": "Taiho Shichau zo",
        "url_adkami": "https://www.adkami.com/anime/3755",
        "source": "Enigme_et_Policier",
        "score_mal": 7.53,
        "popularite_members": 36179,
        "image_url": "https://myanimelist.net/images/anime/1498/97153.jpg"
    },
    {
        "titre_affiche": "Hero Mask",
        "titre_recherche": "Hero Mask",
        "url_adkami": "https://www.adkami.com/anime/3201",
        "source": "Enigme_et_Policier",
        "score_mal": 6.28,
        "popularite_members": 35226,
        "image_url": "https://myanimelist.net/images/anime/1934/96007.jpg"
    },
    {
        "titre_affiche": "Hero Mask",
        "titre_recherche": "Hero Mask",
        "url_adkami": "https://www.adkami.com/anime/3201",
        "source": "Enigme_et_Policier",
        "score_mal": 6.28,
        "popularite_members": 35226,
        "image_url": "https://myanimelist.net/images/anime/1934/96007.jpg"
    },
    {
        "titre_affiche": "Meitantei Conan: Episode One - Chiisaku Natta Meitantei",
        "titre_recherche": "Meitantei Conan: Episode One - Chiisaku Natta Meitantei",
        "url_adkami": "https://www.adkami.com/anime/5123",
        "source": "Enigme_et_Policier",
        "score_mal": 8.26,
        "popularite_members": 34603,
        "image_url": "https://myanimelist.net/images/anime/5/81968.jpg"
    },
    {
        "titre_affiche": "Meitantei Conan: Episode One - Chiisaku Natta Meitantei",
        "titre_recherche": "Meitantei Conan: Episode One - Chiisaku Natta Meitantei",
        "url_adkami": "https://www.adkami.com/anime/5123",
        "source": "Enigme_et_Policier",
        "score_mal": 8.26,
        "popularite_members": 34603,
        "image_url": "https://myanimelist.net/images/anime/5/81968.jpg"
    },
    {
        "titre_affiche": "Yondemasu yo, Azazel-san.",
        "titre_recherche": "Yondemasu yo, Azazel-san.",
        "url_adkami": "https://www.adkami.com/anime/630",
        "source": "Enigme_et_Policier",
        "score_mal": 7.57,
        "popularite_members": 34093,
        "image_url": "https://myanimelist.net/images/anime/2/24619.jpg"
    },
    {
        "titre_affiche": "Yondemasu yo, Azazel-san.",
        "titre_recherche": "Yondemasu yo, Azazel-san.",
        "url_adkami": "https://www.adkami.com/anime/630",
        "source": "Enigme_et_Policier",
        "score_mal": 7.57,
        "popularite_members": 34093,
        "image_url": "https://myanimelist.net/images/anime/2/24619.jpg"
    },
    {
        "titre_affiche": "Ingress: The Animation",
        "titre_recherche": "Ingress: The Animation",
        "url_adkami": "https://www.adkami.com/anime/3141",
        "source": "Enigme_et_Policier",
        "score_mal": 6.28,
        "popularite_members": 31621,
        "image_url": "https://myanimelist.net/images/anime/1944/93421.jpg"
    },
    {
        "titre_affiche": "Ingress: The Animation",
        "titre_recherche": "Ingress: The Animation",
        "url_adkami": "https://www.adkami.com/anime/3141",
        "source": "Enigme_et_Policier",
        "score_mal": 6.28,
        "popularite_members": 31621,
        "image_url": "https://myanimelist.net/images/anime/1944/93421.jpg"
    },
    {
        "titre_affiche": "Layton Kyouju to Eien no Utahime",
        "titre_recherche": "Layton Kyouju to Eien no Utahime",
        "url_adkami": "https://www.adkami.com/anime/3063",
        "source": "Enigme_et_Policier",
        "score_mal": 7.65,
        "popularite_members": 31319,
        "image_url": "https://myanimelist.net/images/anime/3/25873.jpg"
    },
    {
        "titre_affiche": "Layton Kyouju to Eien no Utahime",
        "titre_recherche": "Layton Kyouju to Eien no Utahime",
        "url_adkami": "https://www.adkami.com/anime/3063",
        "source": "Enigme_et_Policier",
        "score_mal": 7.65,
        "popularite_members": 31319,
        "image_url": "https://myanimelist.net/images/anime/3/25873.jpg"
    },
    {
        "titre_affiche": "Real Drive",
        "titre_recherche": "Real Drive",
        "url_adkami": "https://www.adkami.com/anime/1402",
        "source": "Enigme_et_Policier",
        "score_mal": 7.13,
        "popularite_members": 31280,
        "image_url": "https://myanimelist.net/images/anime/6/18929.jpg"
    },
    {
        "titre_affiche": "Nazotoki wa Dinner no Ato de",
        "titre_recherche": "Nazotoki wa Dinner no Ato de",
        "url_adkami": "https://www.adkami.com/anime/5573",
        "source": "Enigme_et_Policier",
        "score_mal": 6.47,
        "popularite_members": 30502,
        "image_url": "https://myanimelist.net/images/anime/1118/149222.jpg"
    },
    {
        "titre_affiche": "Nazotoki wa Dinner no Ato de",
        "titre_recherche": "Nazotoki wa Dinner no Ato de",
        "url_adkami": "https://www.adkami.com/anime/5573",
        "source": "Enigme_et_Policier",
        "score_mal": 6.47,
        "popularite_members": 30502,
        "image_url": "https://myanimelist.net/images/anime/1118/149222.jpg"
    },
    {
        "titre_affiche": "Kitsutsuki Tanteidokoro",
        "titre_recherche": "Kitsutsuki Tanteidokoro",
        "url_adkami": "https://www.adkami.com/anime/3788",
        "source": "Enigme_et_Policier",
        "score_mal": 6.17,
        "popularite_members": 29869,
        "image_url": "https://myanimelist.net/images/anime/1139/105873.jpg"
    },
    {
        "titre_affiche": "Kitsutsuki Tanteidokoro",
        "titre_recherche": "Kitsutsuki Tanteidokoro",
        "url_adkami": "https://www.adkami.com/anime/3788",
        "source": "Enigme_et_Policier",
        "score_mal": 6.17,
        "popularite_members": 29869,
        "image_url": "https://myanimelist.net/images/anime/1139/105873.jpg"
    },
    {
        "titre_affiche": "Angel Cop",
        "titre_recherche": "Angel Cop",
        "url_adkami": "https://www.adkami.com/anime/662",
        "source": "Enigme_et_Policier",
        "score_mal": 6.07,
        "popularite_members": 28195,
        "image_url": "https://myanimelist.net/images/anime/1377/110296.jpg"
    },
    {
        "titre_affiche": "Angel Cop",
        "titre_recherche": "Angel Cop",
        "url_adkami": "https://www.adkami.com/anime/662",
        "source": "Enigme_et_Policier",
        "score_mal": 6.07,
        "popularite_members": 28195,
        "image_url": "https://myanimelist.net/images/anime/1377/110296.jpg"
    },
    {
        "titre_affiche": "Switch",
        "titre_recherche": "Switch",
        "url_adkami": "https://www.adkami.com/anime/1538",
        "source": "Enigme_et_Policier",
        "score_mal": 6.83,
        "popularite_members": 27976,
        "image_url": "https://myanimelist.net/images/anime/3/26316.jpg"
    },
    {
        "titre_affiche": "Switch",
        "titre_recherche": "Switch",
        "url_adkami": "https://www.adkami.com/anime/1538",
        "source": "Enigme_et_Policier",
        "score_mal": 6.83,
        "popularite_members": 27976,
        "image_url": "https://myanimelist.net/images/anime/3/26316.jpg"
    },
    {
        "titre_affiche": "Mezzo DSA",
        "titre_recherche": "Mezzo DSA",
        "url_adkami": "https://www.adkami.com/anime/3387",
        "source": "Enigme_et_Policier",
        "score_mal": 6.7,
        "popularite_members": 27366,
        "image_url": "https://myanimelist.net/images/anime/9/3235.jpg"
    },
    {
        "titre_affiche": "Mezzo DSA",
        "titre_recherche": "Mezzo DSA",
        "url_adkami": "https://www.adkami.com/anime/3387",
        "source": "Enigme_et_Policier",
        "score_mal": 6.7,
        "popularite_members": 27366,
        "image_url": "https://myanimelist.net/images/anime/9/3235.jpg"
    },
    {
        "titre_affiche": "Lupin III: Part 6",
        "titre_recherche": "Lupin III: Part 6",
        "url_adkami": "https://www.adkami.com/anime/4494",
        "source": "Enigme_et_Policier",
        "score_mal": 7.25,
        "popularite_members": 25528,
        "image_url": "https://myanimelist.net/images/anime/1976/118542.jpg"
    },
    {
        "titre_affiche": "Lupin III: Part 6",
        "titre_recherche": "Lupin III: Part 6",
        "url_adkami": "https://www.adkami.com/anime/4494",
        "source": "Enigme_et_Policier",
        "score_mal": 7.25,
        "popularite_members": 25528,
        "image_url": "https://myanimelist.net/images/anime/1976/118542.jpg"
    },
    {
        "titre_affiche": "You're my Loveprize in Viewfinder",
        "titre_recherche": "You're my Loveprize in Viewfinder",
        "url_adkami": "https://www.adkami.com/anime/1491",
        "source": "Enigme_et_Policier",
        "score_mal": 6.45,
        "popularite_members": 22728,
        "image_url": "https://myanimelist.net/images/anime/2/36823.jpg"
    },
    {
        "titre_affiche": "Vampire Holmes",
        "titre_recherche": "Vampire Holmes",
        "url_adkami": "https://www.adkami.com/anime/1415",
        "source": "Enigme_et_Policier",
        "score_mal": 3.34,
        "popularite_members": 22446,
        "image_url": "https://myanimelist.net/images/anime/12/74765.jpg"
    },
    {
        "titre_affiche": "Arne no Jikenbo",
        "titre_recherche": "Arne no Jikenbo",
        "url_adkami": "https://www.adkami.com/anime/5947",
        "source": "Enigme_et_Policier",
        "score_mal": 6.27,
        "popularite_members": 22325,
        "image_url": "https://myanimelist.net/images/anime/1440/154894.jpg"
    },
    {
        "titre_affiche": "Arne no Jikenbo",
        "titre_recherche": "Arne no Jikenbo",
        "url_adkami": "https://www.adkami.com/anime/5947",
        "source": "Enigme_et_Policier",
        "score_mal": 6.27,
        "popularite_members": 22325,
        "image_url": "https://myanimelist.net/images/anime/1440/154894.jpg"
    },
    {
        "titre_affiche": "Heat Guy J",
        "titre_recherche": "Heat Guy J",
        "url_adkami": "https://www.adkami.com/anime/3415",
        "source": "Enigme_et_Policier",
        "score_mal": 7.18,
        "popularite_members": 21408,
        "image_url": "https://myanimelist.net/images/anime/10/76288.jpg"
    },
    {
        "titre_affiche": "Heat Guy J",
        "titre_recherche": "Heat Guy J",
        "url_adkami": "https://www.adkami.com/anime/3415",
        "source": "Enigme_et_Policier",
        "score_mal": 7.18,
        "popularite_members": 21408,
        "image_url": "https://myanimelist.net/images/anime/10/76288.jpg"
    },
    {
        "titre_affiche": "Kindaichi Shounen no Jikenbo Returns",
        "titre_recherche": "Kindaichi Shounen no Jikenbo Returns",
        "url_adkami": "https://www.adkami.com/anime/1113",
        "source": "Enigme_et_Policier",
        "score_mal": 7.58,
        "popularite_members": 20607,
        "image_url": "https://myanimelist.net/images/anime/7/61271.jpg"
    },
    {
        "titre_affiche": "Kindaichi Shounen no Jikenbo Returns",
        "titre_recherche": "Kindaichi Shounen no Jikenbo Returns",
        "url_adkami": "https://www.adkami.com/anime/1113",
        "source": "Enigme_et_Policier",
        "score_mal": 7.58,
        "popularite_members": 20607,
        "image_url": "https://myanimelist.net/images/anime/7/61271.jpg"
    },
    {
        "titre_affiche": "Cutey Honey",
        "titre_recherche": "Cutey Honey",
        "url_adkami": "https://www.adkami.com/anime/4764",
        "source": "Enigme_et_Policier",
        "score_mal": 6.48,
        "popularite_members": 19848,
        "image_url": "https://myanimelist.net/images/anime/13/55427.jpg"
    },
    {
        "titre_affiche": "Cutey Honey",
        "titre_recherche": "Cutey Honey",
        "url_adkami": "https://www.adkami.com/anime/4764",
        "source": "Enigme_et_Policier",
        "score_mal": 6.48,
        "popularite_members": 19848,
        "image_url": "https://myanimelist.net/images/anime/13/55427.jpg"
    },
    {
        "titre_affiche": "Mata Korosarete Shimatta no desu ne, Tantei-sama",
        "titre_recherche": "Mata Korosarete Shimatta no desu ne, Tantei-sama",
        "url_adkami": "https://www.adkami.com/anime/6013",
        "source": "Enigme_et_Policier",
        "score_mal": 6.63,
        "popularite_members": 18671,
        "image_url": "https://myanimelist.net/images/anime/1595/156152.jpg"
    },
    {
        "titre_affiche": "Mata Korosarete Shimatta no desu ne, Tantei-sama",
        "titre_recherche": "Mata Korosarete Shimatta no desu ne, Tantei-sama",
        "url_adkami": "https://www.adkami.com/anime/6013",
        "source": "Enigme_et_Policier",
        "score_mal": 6.63,
        "popularite_members": 18671,
        "image_url": "https://myanimelist.net/images/anime/1595/156152.jpg"
    },
    {
        "titre_affiche": "Crystal blaze",
        "titre_recherche": "Crystal blaze",
        "url_adkami": "https://www.adkami.com/anime/1359",
        "source": "Enigme_et_Policier",
        "score_mal": 6.13,
        "popularite_members": 17750,
        "image_url": "https://myanimelist.net/images/anime/12/21159.jpg"
    },
    {
        "titre_affiche": "Aiyou de Mishi",
        "titre_recherche": "Aiyou de Mishi",
        "url_adkami": "https://www.adkami.com/anime/4875",
        "source": "Enigme_et_Policier",
        "score_mal": 7.2,
        "popularite_members": 17649,
        "image_url": "https://myanimelist.net/images/anime/1667/135309.jpg"
    },
    {
        "titre_affiche": "Aiyou de Mishi",
        "titre_recherche": "Aiyou de Mishi",
        "url_adkami": "https://www.adkami.com/anime/4875",
        "source": "Enigme_et_Policier",
        "score_mal": 7.2,
        "popularite_members": 17649,
        "image_url": "https://myanimelist.net/images/anime/1667/135309.jpg"
    },
    {
        "titre_affiche": "Meitantei Conan: Zero no Tea Time",
        "titre_recherche": "Meitantei Conan: Zero no Tea Time",
        "url_adkami": "https://www.adkami.com/anime/4596",
        "source": "Enigme_et_Policier",
        "score_mal": 6.99,
        "popularite_members": 17013,
        "image_url": "https://myanimelist.net/images/anime/1445/121082.jpg"
    },
    {
        "titre_affiche": "Meitantei Conan: Zero no Tea Time",
        "titre_recherche": "Meitantei Conan: Zero no Tea Time",
        "url_adkami": "https://www.adkami.com/anime/4596",
        "source": "Enigme_et_Policier",
        "score_mal": 6.99,
        "popularite_members": 17013,
        "image_url": "https://myanimelist.net/images/anime/1445/121082.jpg"
    },
    {
        "titre_affiche": "Lupin the IIIrd: Mine Fujiko no Uso",
        "titre_recherche": "Lupin the IIIrd: Mine Fujiko no Uso",
        "url_adkami": "https://www.adkami.com/anime/4893",
        "source": "Enigme_et_Policier",
        "score_mal": 7.3,
        "popularite_members": 16510,
        "image_url": "https://myanimelist.net/images/anime/1376/100562.jpg"
    },
    {
        "titre_affiche": "Lupin the IIIrd: Mine Fujiko no Uso",
        "titre_recherche": "Lupin the IIIrd: Mine Fujiko no Uso",
        "url_adkami": "https://www.adkami.com/anime/4893",
        "source": "Enigme_et_Policier",
        "score_mal": 7.3,
        "popularite_members": 16510,
        "image_url": "https://myanimelist.net/images/anime/1376/100562.jpg"
    },
    {
        "titre_affiche": "Chuuzenji-sensei Mononoke Kougiroku: Sensei ga Nazo wo Hodoite Shimau kara.",
        "titre_recherche": "Chuuzenji-sensei Mononoke Kougiroku: Sensei ga Nazo wo Hodoite Shimau kara.",
        "url_adkami": "https://www.adkami.com/anime/5623",
        "source": "Enigme_et_Policier",
        "score_mal": 6.57,
        "popularite_members": 16432,
        "image_url": "https://myanimelist.net/images/anime/1770/148195.jpg"
    },
    {
        "titre_affiche": "Chuuzenji-sensei Mononoke Kougiroku: Sensei ga Nazo wo Hodoite Shimau kara.",
        "titre_recherche": "Chuuzenji-sensei Mononoke Kougiroku: Sensei ga Nazo wo Hodoite Shimau kara.",
        "url_adkami": "https://www.adkami.com/anime/5623",
        "source": "Enigme_et_Policier",
        "score_mal": 6.57,
        "popularite_members": 16432,
        "image_url": "https://myanimelist.net/images/anime/1770/148195.jpg"
    },
    {
        "titre_affiche": "Meitantei Conan: Hannin no Hanzawa-san",
        "titre_recherche": "Meitantei Conan: Hannin no Hanzawa-san",
        "url_adkami": "https://www.adkami.com/anime/4738",
        "source": "Enigme_et_Policier",
        "score_mal": 6.9,
        "popularite_members": 16121,
        "image_url": "https://myanimelist.net/images/anime/1560/125527.jpg"
    },
    {
        "titre_affiche": "Meitantei Conan: Hannin no Hanzawa-san",
        "titre_recherche": "Meitantei Conan: Hannin no Hanzawa-san",
        "url_adkami": "https://www.adkami.com/anime/4738",
        "source": "Enigme_et_Policier",
        "score_mal": 6.9,
        "popularite_members": 16121,
        "image_url": "https://myanimelist.net/images/anime/1560/125527.jpg"
    },
    {
        "titre_affiche": "Appleseed XIII",
        "titre_recherche": "Appleseed XIII",
        "url_adkami": "https://www.adkami.com/anime/1091",
        "source": "Enigme_et_Policier",
        "score_mal": 6.25,
        "popularite_members": 15289,
        "image_url": "https://myanimelist.net/images/anime/5/28796.jpg"
    },
    {
        "titre_affiche": "Meitantei Holmes",
        "titre_recherche": "Meitantei Holmes",
        "url_adkami": "https://www.adkami.com/anime/3028",
        "source": "Enigme_et_Policier",
        "score_mal": 7.42,
        "popularite_members": 15051,
        "image_url": "https://myanimelist.net/images/anime/4/75723.jpg"
    },
    {
        "titre_affiche": "Tantei Team KZ Jiken Note",
        "titre_recherche": "Tantei Team KZ Jiken Note",
        "url_adkami": "https://www.adkami.com/anime/1609",
        "source": "Enigme_et_Policier",
        "score_mal": 6.18,
        "popularite_members": 14989,
        "image_url": "https://myanimelist.net/images/anime/12/76574.jpg"
    },
    {
        "titre_affiche": "Burn Up! W",
        "titre_recherche": "Burn Up! W",
        "url_adkami": "https://www.adkami.com/anime/4563",
        "source": "Enigme_et_Policier",
        "score_mal": 6.44,
        "popularite_members": 14328,
        "image_url": "https://myanimelist.net/images/anime/1805/96595.jpg"
    },
    {
        "titre_affiche": "Burn Up! W",
        "titre_recherche": "Burn Up! W",
        "url_adkami": "https://www.adkami.com/anime/4563",
        "source": "Enigme_et_Policier",
        "score_mal": 6.44,
        "popularite_members": 14328,
        "image_url": "https://myanimelist.net/images/anime/1805/96595.jpg"
    },
    {
        "titre_affiche": "Nazotokine",
        "titre_recherche": "Nazotokine",
        "url_adkami": "https://www.adkami.com/anime/1929",
        "source": "Enigme_et_Policier",
        "score_mal": 4.81,
        "popularite_members": 13665,
        "image_url": "https://myanimelist.net/images/anime/4/81048.jpg"
    },
    {
        "titre_affiche": "Chocolate Underground",
        "titre_recherche": "Chocolate Underground",
        "url_adkami": "https://www.adkami.com/anime/4312",
        "source": "Enigme_et_Policier",
        "score_mal": 6.07,
        "popularite_members": 12874,
        "image_url": "https://myanimelist.net/images/anime/8/12400.jpg"
    },
    {
        "titre_affiche": "Chocolate Underground",
        "titre_recherche": "Chocolate Underground",
        "url_adkami": "https://www.adkami.com/anime/4312",
        "source": "Enigme_et_Policier",
        "score_mal": 6.07,
        "popularite_members": 12874,
        "image_url": "https://myanimelist.net/images/anime/8/12400.jpg"
    },
    {
        "titre_affiche": "Burn Up! Scramble",
        "titre_recherche": "Burn Up! Scramble",
        "url_adkami": "https://www.adkami.com/anime/1719",
        "source": "Enigme_et_Policier",
        "score_mal": 6.14,
        "popularite_members": 11393,
        "image_url": "https://myanimelist.net/images/anime/12/75500.jpg"
    },
    {
        "titre_affiche": "Burn Up! Scramble",
        "titre_recherche": "Burn Up! Scramble",
        "url_adkami": "https://www.adkami.com/anime/1719",
        "source": "Enigme_et_Policier",
        "score_mal": 6.14,
        "popularite_members": 11393,
        "image_url": "https://myanimelist.net/images/anime/12/75500.jpg"
    },
    {
        "titre_affiche": "Miami Guns",
        "titre_recherche": "Miami Guns",
        "url_adkami": "https://www.adkami.com/anime/3059",
        "source": "Enigme_et_Policier",
        "score_mal": 6.63,
        "popularite_members": 8996,
        "image_url": "https://myanimelist.net/images/anime/1/783.jpg"
    },
    {
        "titre_affiche": "Miami Guns",
        "titre_recherche": "Miami Guns",
        "url_adkami": "https://www.adkami.com/anime/3059",
        "source": "Enigme_et_Policier",
        "score_mal": 6.63,
        "popularite_members": 8996,
        "image_url": "https://myanimelist.net/images/anime/1/783.jpg"
    },
    {
        "titre_affiche": "Agatha Christie's Great Detectives Poirot",
        "titre_recherche": "Agatha Christie's Great Detectives Poirot",
        "url_adkami": "https://www.adkami.com/anime/294",
        "source": "Enigme_et_Policier",
        "score_mal": 6.96,
        "popularite_members": 8849,
        "image_url": "https://myanimelist.net/images/anime/6/3149.jpg"
    },
    {
        "titre_affiche": "Koroshiya-san",
        "titre_recherche": "Koroshiya-san",
        "url_adkami": "https://www.adkami.com/anime/968",
        "source": "Enigme_et_Policier",
        "score_mal": 5.49,
        "popularite_members": 7954,
        "image_url": "https://myanimelist.net/images/anime/11/55531.jpg"
    },
    {
        "titre_affiche": "Koroshiya-san",
        "titre_recherche": "Koroshiya-san",
        "url_adkami": "https://www.adkami.com/anime/968",
        "source": "Enigme_et_Policier",
        "score_mal": 5.49,
        "popularite_members": 7954,
        "image_url": "https://myanimelist.net/images/anime/11/55531.jpg"
    },
    {
        "titre_affiche": "Aoyama Goushou Tanpenshuu",
        "titre_recherche": "Aoyama Goushou Tanpenshuu",
        "url_adkami": "https://www.adkami.com/anime/5791",
        "source": "Enigme_et_Policier",
        "score_mal": 7.27,
        "popularite_members": 7120,
        "image_url": "https://myanimelist.net/images/anime/2/28783.jpg"
    },
    {
        "titre_affiche": "Aoyama Goushou Tanpenshuu",
        "titre_recherche": "Aoyama Goushou Tanpenshuu",
        "url_adkami": "https://www.adkami.com/anime/5791",
        "source": "Enigme_et_Policier",
        "score_mal": 7.27,
        "popularite_members": 7120,
        "image_url": "https://myanimelist.net/images/anime/2/28783.jpg"
    },
    {
        "titre_affiche": "Li Shi Zhentan Shiwusuo: A Day in Lungmen",
        "titre_recherche": "Li Shi Zhentan Shiwusuo: A Day in Lungmen",
        "url_adkami": "https://www.adkami.com/anime/4776",
        "source": "Enigme_et_Policier",
        "score_mal": 6.52,
        "popularite_members": 5689,
        "image_url": "https://myanimelist.net/images/anime/1641/131849.jpg"
    },
    {
        "titre_affiche": "Li Shi Zhentan Shiwusuo: A Day in Lungmen",
        "titre_recherche": "Li Shi Zhentan Shiwusuo: A Day in Lungmen",
        "url_adkami": "https://www.adkami.com/anime/4776",
        "source": "Enigme_et_Policier",
        "score_mal": 6.52,
        "popularite_members": 5689,
        "image_url": "https://myanimelist.net/images/anime/1641/131849.jpg"
    },
    {
        "titre_affiche": "Lupin III vs. Cat's Eye",
        "titre_recherche": "Lupin III vs. Cat's Eye",
        "url_adkami": "https://www.adkami.com/anime/5903",
        "source": "Enigme_et_Policier",
        "score_mal": 6.63,
        "popularite_members": 5503,
        "image_url": "https://myanimelist.net/images/anime/1326/131658.jpg"
    },
    {
        "titre_affiche": "Lupin III vs. Cat's Eye",
        "titre_recherche": "Lupin III vs. Cat's Eye",
        "url_adkami": "https://www.adkami.com/anime/5903",
        "source": "Enigme_et_Policier",
        "score_mal": 6.63,
        "popularite_members": 5503,
        "image_url": "https://myanimelist.net/images/anime/1326/131658.jpg"
    },
    {
        "titre_affiche": "Lupin the IIIrd the Movie: Fujimi no Ketsuzoku",
        "titre_recherche": "Lupin the IIIrd the Movie: Fujimi no Ketsuzoku",
        "url_adkami": "https://www.adkami.com/anime/5882",
        "source": "Enigme_et_Policier",
        "score_mal": 6.8,
        "popularite_members": 5403,
        "image_url": "https://myanimelist.net/images/anime/1374/149826.jpg"
    },
    {
        "titre_affiche": "Lupin the IIIrd the Movie: Fujimi no Ketsuzoku",
        "titre_recherche": "Lupin the IIIrd the Movie: Fujimi no Ketsuzoku",
        "url_adkami": "https://www.adkami.com/anime/5882",
        "source": "Enigme_et_Policier",
        "score_mal": 6.8,
        "popularite_members": 5403,
        "image_url": "https://myanimelist.net/images/anime/1374/149826.jpg"
    },
    {
        "titre_affiche": "Itazura Majo to Nemuranai Machi",
        "titre_recherche": "Itazura Majo to Nemuranai Machi",
        "url_adkami": "https://www.adkami.com/anime/2550",
        "source": "Enigme_et_Policier",
        "score_mal": 5.91,
        "popularite_members": 5279,
        "image_url": "https://myanimelist.net/images/anime/3/89169.jpg"
    },
    {
        "titre_affiche": "Itazura Majo to Nemuranai Machi",
        "titre_recherche": "Itazura Majo to Nemuranai Machi",
        "url_adkami": "https://www.adkami.com/anime/2550",
        "source": "Enigme_et_Policier",
        "score_mal": 5.91,
        "popularite_members": 5279,
        "image_url": "https://myanimelist.net/images/anime/3/89169.jpg"
    },
    {
        "titre_affiche": "Meitantei Conan: Haibara Ai Monogatari - Kurogane no Mystery Train",
        "titre_recherche": "Meitantei Conan: Haibara Ai Monogatari - Kurogane no Mystery Train",
        "url_adkami": "https://www.adkami.com/anime/5792",
        "source": "Enigme_et_Policier",
        "score_mal": 7.38,
        "popularite_members": 4883,
        "image_url": "https://myanimelist.net/images/anime/1285/131672.jpg"
    },
    {
        "titre_affiche": "Meitantei Conan: Haibara Ai Monogatari - Kurogane no Mystery Train",
        "titre_recherche": "Meitantei Conan: Haibara Ai Monogatari - Kurogane no Mystery Train",
        "url_adkami": "https://www.adkami.com/anime/5792",
        "source": "Enigme_et_Policier",
        "score_mal": 7.38,
        "popularite_members": 4883,
        "image_url": "https://myanimelist.net/images/anime/1285/131672.jpg"
    },
    {
        "titre_affiche": "Lupin the IIIrd: Zenigata to Futari no Lupin",
        "titre_recherche": "Lupin the IIIrd: Zenigata to Futari no Lupin",
        "url_adkami": "https://www.adkami.com/anime/5879",
        "source": "Enigme_et_Policier",
        "score_mal": 7.28,
        "popularite_members": 3899,
        "image_url": "https://myanimelist.net/images/anime/1283/150650.jpg"
    },
    {
        "titre_affiche": "Lupin the IIIrd: Zenigata to Futari no Lupin",
        "titre_recherche": "Lupin the IIIrd: Zenigata to Futari no Lupin",
        "url_adkami": "https://www.adkami.com/anime/5879",
        "source": "Enigme_et_Policier",
        "score_mal": 7.28,
        "popularite_members": 3899,
        "image_url": "https://myanimelist.net/images/anime/1283/150650.jpg"
    },
    {
        "titre_affiche": "Mirai Keisatsu Urashiman",
        "titre_recherche": "Mirai Keisatsu Urashiman",
        "url_adkami": "https://www.adkami.com/anime/417",
        "source": "Enigme_et_Policier",
        "score_mal": 7.2,
        "popularite_members": 3598,
        "image_url": "https://myanimelist.net/images/anime/1605/91989.jpg"
    },
    {
        "titre_affiche": "Mirai Keisatsu Urashiman",
        "titre_recherche": "Mirai Keisatsu Urashiman",
        "url_adkami": "https://www.adkami.com/anime/417",
        "source": "Enigme_et_Policier",
        "score_mal": 7.2,
        "popularite_members": 3598,
        "image_url": "https://myanimelist.net/images/anime/1605/91989.jpg"
    },
    {
        "titre_affiche": "Tenchi Muyou! GXP: Paradise Shidou-hen",
        "titre_recherche": "Tenchi Muyou! GXP: Paradise Shidou-hen",
        "url_adkami": "https://www.adkami.com/anime/4907",
        "source": "Enigme_et_Policier",
        "score_mal": 6.3,
        "popularite_members": 3336,
        "image_url": "https://myanimelist.net/images/anime/1169/134697.jpg"
    },
    {
        "titre_affiche": "Tenchi Muyou! GXP: Paradise Shidou-hen",
        "titre_recherche": "Tenchi Muyou! GXP: Paradise Shidou-hen",
        "url_adkami": "https://www.adkami.com/anime/4907",
        "source": "Enigme_et_Policier",
        "score_mal": 6.3,
        "popularite_members": 3336,
        "image_url": "https://myanimelist.net/images/anime/1169/134697.jpg"
    },
    {
        "titre_affiche": "Chou Shounen Tanteidan Neo",
        "titre_recherche": "Chou Shounen Tanteidan Neo",
        "url_adkami": "https://www.adkami.com/anime/1980",
        "source": "Enigme_et_Policier",
        "score_mal": 5.15,
        "popularite_members": 3038,
        "image_url": "https://myanimelist.net/images/anime/1346/139321.jpg"
    },
    {
        "titre_affiche": "Chou Shounen Tanteidan Neo",
        "titre_recherche": "Chou Shounen Tanteidan Neo",
        "url_adkami": "https://www.adkami.com/anime/1980",
        "source": "Enigme_et_Policier",
        "score_mal": 5.15,
        "popularite_members": 3038,
        "image_url": "https://myanimelist.net/images/anime/1346/139321.jpg"
    },
    {
        "titre_affiche": "Monster",
        "titre_recherche": "Monster",
        "url_adkami": "https://www.adkami.com/anime/307",
        "source": "Enigme_et_Policier",
        "score_mal": null,
        "popularite_members": 196,
        "image_url": "https://myanimelist.net/images/anime/1648/152231.jpg"
    },
    {
        "titre_affiche": "Monster",
        "titre_recherche": "Monster",
        "url_adkami": "https://www.adkami.com/anime/307",
        "source": "Enigme_et_Policier",
        "score_mal": null,
        "popularite_members": 196,
        "image_url": "https://myanimelist.net/images/anime/1648/152231.jpg"
    }
]